LICENSE
MANIFEST.in
README.md
requirements.txt
setup.py
youtube/__init__.py
youtube/settings.py
youtube/data/__init__.py
youtube/data/api.py
youtube/data/exceptions.py
youtube/data/tests.py
youtube/data/utils.py
youtube/data/resources/__init__.py
youtube/data/resources/fields.py
youtube/data/resources/nested_fields.py
youtube/data/resources/types.py
youtube_api_wrapper.egg-info/PKG-INFO
youtube_api_wrapper.egg-info/SOURCES.txt
youtube_api_wrapper.egg-info/dependency_links.txt
youtube_api_wrapper.egg-info/requires.txt
youtube_api_wrapper.egg-info/top_level.txt